<templateSet group="PHP Unit">
  <template name="_t" value="/** @test */&#10;public function $NAME$()&#10;{&#10;    $END$&#10;}" description="Test Method" toReformat="false" toShortenFQNames="true">
    <variable name="NAME" expression="" defaultValue="" alwaysStopAt="true" />
    <context>
      <option name="PHP" value="true" />
    </context>
  </template>
  <template name="_st" value="protected function setUp(): void&#10;{&#10;    $END$&#10;}" description="Set Up" toReformat="false" toShortenFQNames="true">
    <context>
      <option name="PHP" value="true" />
    </context>
  </template>
</templateSet>